xiudb/__init__.py
xiudb/xiudb.py
xiudb_Peiiii-0.0.2.dist-info/LICENSE
xiudb_Peiiii-0.0.2.dist-info/METADATA
xiudb_Peiiii-0.0.2.dist-info/WHEEL
xiudb_Peiiii-0.0.2.dist-info/top_level.txt
xiudb_Peiiii-0.0.2.dist-info/RECORD
