Metadata-Version: 2.1
Name: xiudb-Peiiii
Version: 0.0.2
Summary: This is a simple package, which can be used as a substitute of database.
